fckbvffkg/__init__.py
fckbvffkg/core.py
fckbvffkg/log.py
fckbvffkg/server.py
fckbvffkg-0.1.1.dist-info/METADATA
fckbvffkg-0.1.1.dist-info/WHEEL
fckbvffkg-0.1.1.dist-info/top_level.txt
fckbvffkg-0.1.1.dist-info/RECORD
